setup.py
python_controlsystems.egg-info/PKG-INFO
python_controlsystems.egg-info/SOURCES.txt
python_controlsystems.egg-info/dependency_links.txt
python_controlsystems.egg-info/top_level.txt
src/__init__.py
src/chienhronesreswick0.py
src/chienhronesreswick20.py
src/cohencoon.py
src/error.py
src/euler.py
src/gettimenear.py
src/matrix.py
src/polynomial.py
src/rk2.py
src/rk3.py
src/rk4.py
src/statespace.py
src/transferfunction.py
src/zieglernichols.py