Metadata-Version: 1.0
Name: python-controlsystems
Version: 0.2.1
Summary: A python library for study of control systems
Home-page: http://bitbucket.org/rafaelmartins/python-controlsystems/
Author: ['Rafael G. Martins']
Author-email: ['rafael@rafaelmartins.com']
License: GPL2
Platform: UNKNOWN
